package com.tencent.tmassistantsdk.e;

class c
  implements Runnable
{
  c(b paramb, String paramString)
  {
  }

  // ERROR //
  public void run()
  {
    // Byte code:
    //   0: aload_0
    //   1: getfield 16	com/tencent/tmassistantsdk/e/c:a	Ljava/lang/String;
    //   4: astore_1
    //   5: aload_0
    //   6: getfield 14	com/tencent/tmassistantsdk/e/c:b	Lcom/tencent/tmassistantsdk/e/b;
    //   9: new 30	org/apache/http/client/methods/HttpGet
    //   12: dup
    //   13: invokespecial 31	org/apache/http/client/methods/HttpGet:<init>	()V
    //   16: putfield 36	com/tencent/tmassistantsdk/e/b:b	Lorg/apache/http/client/methods/HttpGet;
    //   19: new 38	java/lang/StringBuilder
    //   22: dup
    //   23: invokespecial 39	java/lang/StringBuilder:<init>	()V
    //   26: ldc 41
    //   28: invokevirtual 45	java/lang/StringBuilder:append	(Ljava/lang/String;)Ljava/lang/StringBuilder;
    //   31: aload_1
    //   32: invokevirtual 45	java/lang/StringBuilder:append	(Ljava/lang/String;)Ljava/lang/StringBuilder;
    //   35: invokevirtual 49	java/lang/StringBuilder:toString	()Ljava/lang/String;
    //   38: astore 9
    //   40: aload_0
    //   41: getfield 14	com/tencent/tmassistantsdk/e/c:b	Lcom/tencent/tmassistantsdk/e/b;
    //   44: getfield 36	com/tencent/tmassistantsdk/e/b:b	Lorg/apache/http/client/methods/HttpGet;
    //   47: new 51	java/net/URI
    //   50: dup
    //   51: aload 9
    //   53: invokespecial 54	java/net/URI:<init>	(Ljava/lang/String;)V
    //   56: invokevirtual 58	org/apache/http/client/methods/HttpGet:setURI	(Ljava/net/URI;)V
    //   59: invokestatic 63	com/tencent/tmassistantsdk/downloadservice/k:a	()Lorg/apache/http/client/HttpClient;
    //   62: astore 10
    //   64: aload 10
    //   66: astore_3
    //   67: aload_3
    //   68: invokestatic 66	com/tencent/tmassistantsdk/downloadservice/k:a	(Lorg/apache/http/client/HttpClient;)V
    //   71: aload_3
    //   72: aload_0
    //   73: getfield 14	com/tencent/tmassistantsdk/e/c:b	Lcom/tencent/tmassistantsdk/e/b;
    //   76: getfield 36	com/tencent/tmassistantsdk/e/b:b	Lorg/apache/http/client/methods/HttpGet;
    //   79: invokeinterface 72 2 0
    //   84: astore 11
    //   86: aload 11
    //   88: ifnull +212 -> 300
    //   91: aload 11
    //   93: invokeinterface 78 1 0
    //   98: invokeinterface 84 1 0
    //   103: sipush 200
    //   106: if_icmpne +194 -> 300
    //   109: aload 11
    //   111: invokeinterface 88 1 0
    //   116: astore 12
    //   118: aload 12
    //   120: ifnull +180 -> 300
    //   123: aload 12
    //   125: invokestatic 94	org/apache/http/util/EntityUtils:toByteArray	(Lorg/apache/http/HttpEntity;)[B
    //   128: astore 13
    //   130: aload 13
    //   132: ifnull +127 -> 259
    //   135: aload 13
    //   137: arraylength
    //   138: ifle +121 -> 259
    //   141: new 96	java/lang/String
    //   144: dup
    //   145: aload 13
    //   147: ldc 98
    //   149: invokespecial 101	java/lang/String:<init>	([BLjava/lang/String;)V
    //   152: astore 14
    //   154: aload 14
    //   156: invokestatic 107	android/text/TextUtils:isEmpty	(Ljava/lang/CharSequence;)Z
    //   159: ifne +59 -> 218
    //   162: new 109	org/json/JSONObject
    //   165: dup
    //   166: aload 14
    //   168: invokespecial 110	org/json/JSONObject:<init>	(Ljava/lang/String;)V
    //   171: astore 15
    //   173: ldc 112
    //   175: ldc 114
    //   177: invokestatic 119	com/tencent/tmassistantsdk/g/l:b	(Ljava/lang/String;Ljava/lang/String;)V
    //   180: aload_0
    //   181: getfield 14	com/tencent/tmassistantsdk/e/c:b	Lcom/tencent/tmassistantsdk/e/b;
    //   184: aload 15
    //   186: iconst_0
    //   187: invokevirtual 122	com/tencent/tmassistantsdk/e/b:a	(Lorg/json/JSONObject;I)V
    //   190: aload_0
    //   191: getfield 14	com/tencent/tmassistantsdk/e/c:b	Lcom/tencent/tmassistantsdk/e/b;
    //   194: aconst_null
    //   195: putfield 36	com/tencent/tmassistantsdk/e/b:b	Lorg/apache/http/client/methods/HttpGet;
    //   198: aload_3
    //   199: ifnull +18 -> 217
    //   202: aload_3
    //   203: invokeinterface 126 1 0
    //   208: astore 5
    //   210: aload 5
    //   212: invokeinterface 131 1 0
    //   217: return
    //   218: ldc 112
    //   220: ldc 133
    //   222: invokestatic 119	com/tencent/tmassistantsdk/g/l:b	(Ljava/lang/String;Ljava/lang/String;)V
    //   225: aload_0
    //   226: getfield 14	com/tencent/tmassistantsdk/e/c:b	Lcom/tencent/tmassistantsdk/e/b;
    //   229: aconst_null
    //   230: sipush 606
    //   233: invokevirtual 122	com/tencent/tmassistantsdk/e/b:a	(Lorg/json/JSONObject;I)V
    //   236: aload_0
    //   237: getfield 14	com/tencent/tmassistantsdk/e/c:b	Lcom/tencent/tmassistantsdk/e/b;
    //   240: aconst_null
    //   241: putfield 36	com/tencent/tmassistantsdk/e/b:b	Lorg/apache/http/client/methods/HttpGet;
    //   244: aload_3
    //   245: ifnull -28 -> 217
    //   248: aload_3
    //   249: invokeinterface 126 1 0
    //   254: astore 5
    //   256: goto -46 -> 210
    //   259: ldc 112
    //   261: ldc 135
    //   263: invokestatic 119	com/tencent/tmassistantsdk/g/l:b	(Ljava/lang/String;Ljava/lang/String;)V
    //   266: aload_0
    //   267: getfield 14	com/tencent/tmassistantsdk/e/c:b	Lcom/tencent/tmassistantsdk/e/b;
    //   270: aconst_null
    //   271: sipush 704
    //   274: invokevirtual 122	com/tencent/tmassistantsdk/e/b:a	(Lorg/json/JSONObject;I)V
    //   277: aload_0
    //   278: getfield 14	com/tencent/tmassistantsdk/e/c:b	Lcom/tencent/tmassistantsdk/e/b;
    //   281: aconst_null
    //   282: putfield 36	com/tencent/tmassistantsdk/e/b:b	Lorg/apache/http/client/methods/HttpGet;
    //   285: aload_3
    //   286: ifnull -69 -> 217
    //   289: aload_3
    //   290: invokeinterface 126 1 0
    //   295: astore 5
    //   297: goto -87 -> 210
    //   300: aload_0
    //   301: getfield 14	com/tencent/tmassistantsdk/e/c:b	Lcom/tencent/tmassistantsdk/e/b;
    //   304: aconst_null
    //   305: sipush 704
    //   308: invokevirtual 122	com/tencent/tmassistantsdk/e/b:a	(Lorg/json/JSONObject;I)V
    //   311: aload_0
    //   312: getfield 14	com/tencent/tmassistantsdk/e/c:b	Lcom/tencent/tmassistantsdk/e/b;
    //   315: aconst_null
    //   316: putfield 36	com/tencent/tmassistantsdk/e/b:b	Lorg/apache/http/client/methods/HttpGet;
    //   319: aload_3
    //   320: ifnull -103 -> 217
    //   323: aload_3
    //   324: invokeinterface 126 1 0
    //   329: astore 5
    //   331: goto -121 -> 210
    //   334: astore 8
    //   336: aconst_null
    //   337: astore_3
    //   338: aload 8
    //   340: invokevirtual 138	org/apache/http/conn/ConnectTimeoutException:printStackTrace	()V
    //   343: aload_0
    //   344: getfield 14	com/tencent/tmassistantsdk/e/c:b	Lcom/tencent/tmassistantsdk/e/b;
    //   347: aconst_null
    //   348: sipush 601
    //   351: invokevirtual 122	com/tencent/tmassistantsdk/e/b:a	(Lorg/json/JSONObject;I)V
    //   354: aload_0
    //   355: getfield 14	com/tencent/tmassistantsdk/e/c:b	Lcom/tencent/tmassistantsdk/e/b;
    //   358: aconst_null
    //   359: putfield 36	com/tencent/tmassistantsdk/e/b:b	Lorg/apache/http/client/methods/HttpGet;
    //   362: aload_3
    //   363: ifnull -146 -> 217
    //   366: aload_3
    //   367: invokeinterface 126 1 0
    //   372: astore 5
    //   374: goto -164 -> 210
    //   377: astore 7
    //   379: aconst_null
    //   380: astore_3
    //   381: aload 7
    //   383: invokevirtual 139	java/net/ConnectException:printStackTrace	()V
    //   386: aload_0
    //   387: getfield 14	com/tencent/tmassistantsdk/e/c:b	Lcom/tencent/tmassistantsdk/e/b;
    //   390: aconst_null
    //   391: iconst_1
    //   392: invokevirtual 122	com/tencent/tmassistantsdk/e/b:a	(Lorg/json/JSONObject;I)V
    //   395: aload_0
    //   396: getfield 14	com/tencent/tmassistantsdk/e/c:b	Lcom/tencent/tmassistantsdk/e/b;
    //   399: aconst_null
    //   400: putfield 36	com/tencent/tmassistantsdk/e/b:b	Lorg/apache/http/client/methods/HttpGet;
    //   403: aload_3
    //   404: ifnull -187 -> 217
    //   407: aload_3
    //   408: invokeinterface 126 1 0
    //   413: astore 5
    //   415: goto -205 -> 210
    //   418: astore 6
    //   420: aconst_null
    //   421: astore_3
    //   422: aload 6
    //   424: invokevirtual 140	java/net/SocketTimeoutException:printStackTrace	()V
    //   427: aload_0
    //   428: getfield 14	com/tencent/tmassistantsdk/e/c:b	Lcom/tencent/tmassistantsdk/e/b;
    //   431: aconst_null
    //   432: sipush 602
    //   435: invokevirtual 122	com/tencent/tmassistantsdk/e/b:a	(Lorg/json/JSONObject;I)V
    //   438: aload_0
    //   439: getfield 14	com/tencent/tmassistantsdk/e/c:b	Lcom/tencent/tmassistantsdk/e/b;
    //   442: aconst_null
    //   443: putfield 36	com/tencent/tmassistantsdk/e/b:b	Lorg/apache/http/client/methods/HttpGet;
    //   446: aload_3
    //   447: ifnull -230 -> 217
    //   450: aload_3
    //   451: invokeinterface 126 1 0
    //   456: astore 5
    //   458: goto -248 -> 210
    //   461: astore 4
    //   463: aconst_null
    //   464: astore_3
    //   465: aload 4
    //   467: invokevirtual 141	java/lang/Exception:printStackTrace	()V
    //   470: aload_0
    //   471: getfield 14	com/tencent/tmassistantsdk/e/c:b	Lcom/tencent/tmassistantsdk/e/b;
    //   474: aconst_null
    //   475: sipush 604
    //   478: invokevirtual 122	com/tencent/tmassistantsdk/e/b:a	(Lorg/json/JSONObject;I)V
    //   481: aload_0
    //   482: getfield 14	com/tencent/tmassistantsdk/e/c:b	Lcom/tencent/tmassistantsdk/e/b;
    //   485: aconst_null
    //   486: putfield 36	com/tencent/tmassistantsdk/e/b:b	Lorg/apache/http/client/methods/HttpGet;
    //   489: aload_3
    //   490: ifnull -273 -> 217
    //   493: aload_3
    //   494: invokeinterface 126 1 0
    //   499: astore 5
    //   501: goto -291 -> 210
    //   504: astore_2
    //   505: aconst_null
    //   506: astore_3
    //   507: aload_0
    //   508: getfield 14	com/tencent/tmassistantsdk/e/c:b	Lcom/tencent/tmassistantsdk/e/b;
    //   511: aconst_null
    //   512: putfield 36	com/tencent/tmassistantsdk/e/b:b	Lorg/apache/http/client/methods/HttpGet;
    //   515: aload_3
    //   516: ifnull +14 -> 530
    //   519: aload_3
    //   520: invokeinterface 126 1 0
    //   525: invokeinterface 131 1 0
    //   530: aload_2
    //   531: athrow
    //   532: astore_2
    //   533: goto -26 -> 507
    //   536: astore 4
    //   538: goto -73 -> 465
    //   541: astore 6
    //   543: goto -121 -> 422
    //   546: astore 7
    //   548: goto -167 -> 381
    //   551: astore 8
    //   553: goto -215 -> 338
    //
    // Exception table:
    //   from	to	target	type
    //   5	64	334	org/apache/http/conn/ConnectTimeoutException
    //   5	64	377	java/net/ConnectException
    //   5	64	418	java/net/SocketTimeoutException
    //   5	64	461	java/lang/Exception
    //   5	64	504	finally
    //   67	86	532	finally
    //   91	118	532	finally
    //   123	130	532	finally
    //   135	190	532	finally
    //   218	236	532	finally
    //   259	277	532	finally
    //   300	311	532	finally
    //   338	354	532	finally
    //   381	395	532	finally
    //   422	438	532	finally
    //   465	481	532	finally
    //   67	86	536	java/lang/Exception
    //   91	118	536	java/lang/Exception
    //   123	130	536	java/lang/Exception
    //   135	190	536	java/lang/Exception
    //   218	236	536	java/lang/Exception
    //   259	277	536	java/lang/Exception
    //   300	311	536	java/lang/Exception
    //   67	86	541	java/net/SocketTimeoutException
    //   91	118	541	java/net/SocketTimeoutException
    //   123	130	541	java/net/SocketTimeoutException
    //   135	190	541	java/net/SocketTimeoutException
    //   218	236	541	java/net/SocketTimeoutException
    //   259	277	541	java/net/SocketTimeoutException
    //   300	311	541	java/net/SocketTimeoutException
    //   67	86	546	java/net/ConnectException
    //   91	118	546	java/net/ConnectException
    //   123	130	546	java/net/ConnectException
    //   135	190	546	java/net/ConnectException
    //   218	236	546	java/net/ConnectException
    //   259	277	546	java/net/ConnectException
    //   300	311	546	java/net/ConnectException
    //   67	86	551	org/apache/http/conn/ConnectTimeoutException
    //   91	118	551	org/apache/http/conn/ConnectTimeoutException
    //   123	130	551	org/apache/http/conn/ConnectTimeoutException
    //   135	190	551	org/apache/http/conn/ConnectTimeoutException
    //   218	236	551	org/apache/http/conn/ConnectTimeoutException
    //   259	277	551	org/apache/http/conn/ConnectTimeoutException
    //   300	311	551	org/apache/http/conn/ConnectTimeoutException
  }
}

/* Location:           D:\rm_src\classes_dex2jar\
 * Qualified Name:     com.tencent.tmassistantsdk.e.c
 * JD-Core Version:    0.6.0
 */