package com.pay.image.cache;

final class b
  implements Runnable
{
  b(APImageCache paramAPImageCache)
  {
  }

  // ERROR //
  public final void run()
  {
    // Byte code:
    //   0: aload_0
    //   1: getfield 12	com/pay/image/cache/b:a	Lcom/pay/image/cache/APImageCache;
    //   4: invokestatic 23	com/pay/image/cache/APImageCache:a	(Lcom/pay/image/cache/APImageCache;)Ljava/util/Queue;
    //   7: invokeinterface 29 1 0
    //   12: ifgt +21 -> 33
    //   15: aload_0
    //   16: monitorenter
    //   17: aload_0
    //   18: invokevirtual 32	java/lang/Object:wait	()V
    //   21: aload_0
    //   22: monitorexit
    //   23: goto -23 -> 0
    //   26: astore 8
    //   28: aload_0
    //   29: monitorexit
    //   30: aload 8
    //   32: athrow
    //   33: aload_0
    //   34: monitorenter
    //   35: aload_0
    //   36: getfield 12	com/pay/image/cache/b:a	Lcom/pay/image/cache/APImageCache;
    //   39: invokestatic 23	com/pay/image/cache/APImageCache:a	(Lcom/pay/image/cache/APImageCache;)Ljava/util/Queue;
    //   42: invokeinterface 36 1 0
    //   47: checkcast 38	com/pay/image/cache/APImageCache$ImageRef
    //   50: astore_2
    //   51: aload_0
    //   52: monitorexit
    //   53: ldc 40
    //   55: new 42	java/lang/StringBuilder
    //   58: dup
    //   59: ldc 44
    //   61: invokespecial 47	java/lang/StringBuilder:<init>	(Ljava/lang/String;)V
    //   64: aload_2
    //   65: getfield 51	com/pay/image/cache/APImageCache$ImageRef:b	Ljava/lang/String;
    //   68: invokevirtual 55	java/lang/StringBuilder:append	(Ljava/lang/String;)Ljava/lang/StringBuilder;
    //   71: invokevirtual 59	java/lang/StringBuilder:toString	()Ljava/lang/String;
    //   74: invokestatic 65	com/pay/common/tool/APLog:i	(Ljava/lang/String;Ljava/lang/String;)V
    //   77: aload_2
    //   78: getfield 51	com/pay/image/cache/APImageCache$ImageRef:b	Ljava/lang/String;
    //   81: iconst_1
    //   82: invokestatic 68	com/pay/image/cache/APImageCache:a	(Ljava/lang/String;Z)Landroid/graphics/Bitmap;
    //   85: astore_3
    //   86: aload_3
    //   87: ifnull +51 -> 138
    //   90: aload_2
    //   91: getfield 51	com/pay/image/cache/APImageCache$ImageRef:b	Ljava/lang/String;
    //   94: ifnull +44 -> 138
    //   97: aload_0
    //   98: getfield 12	com/pay/image/cache/b:a	Lcom/pay/image/cache/APImageCache;
    //   101: getfield 72	com/pay/image/cache/APImageCache:mMemoryCache	Landroid/support/v4/util/LruCache;
    //   104: aload_2
    //   105: getfield 51	com/pay/image/cache/APImageCache$ImageRef:b	Ljava/lang/String;
    //   108: aload_3
    //   109: invokevirtual 78	android/support/v4/util/LruCache:put	(Ljava/lang/Object;Ljava/lang/Object;)Ljava/lang/Object;
    //   112: pop
    //   113: aload_0
    //   114: getfield 12	com/pay/image/cache/b:a	Lcom/pay/image/cache/APImageCache;
    //   117: getfield 82	com/pay/image/cache/APImageCache:mDiskCache	Lcom/pay/image/cache/APDiskLruCache;
    //   120: ifnull +18 -> 138
    //   123: aload_0
    //   124: getfield 12	com/pay/image/cache/b:a	Lcom/pay/image/cache/APImageCache;
    //   127: getfield 82	com/pay/image/cache/APImageCache:mDiskCache	Lcom/pay/image/cache/APDiskLruCache;
    //   130: aload_2
    //   131: getfield 51	com/pay/image/cache/APImageCache$ImageRef:b	Ljava/lang/String;
    //   134: aload_3
    //   135: invokevirtual 87	com/pay/image/cache/APDiskLruCache:put	(Ljava/lang/String;Landroid/graphics/Bitmap;)V
    //   138: aload_0
    //   139: getfield 12	com/pay/image/cache/b:a	Lcom/pay/image/cache/APImageCache;
    //   142: invokestatic 90	com/pay/image/cache/APImageCache:b	(Lcom/pay/image/cache/APImageCache;)Landroid/os/Handler;
    //   145: ifnull -145 -> 0
    //   148: aload_0
    //   149: getfield 12	com/pay/image/cache/b:a	Lcom/pay/image/cache/APImageCache;
    //   152: invokestatic 90	com/pay/image/cache/APImageCache:b	(Lcom/pay/image/cache/APImageCache;)Landroid/os/Handler;
    //   155: iconst_0
    //   156: aload_2
    //   157: invokevirtual 96	android/os/Handler:obtainMessage	(ILjava/lang/Object;)Landroid/os/Message;
    //   160: astore 4
    //   162: aload_0
    //   163: getfield 12	com/pay/image/cache/b:a	Lcom/pay/image/cache/APImageCache;
    //   166: invokestatic 90	com/pay/image/cache/APImageCache:b	(Lcom/pay/image/cache/APImageCache;)Landroid/os/Handler;
    //   169: aload 4
    //   171: invokevirtual 100	android/os/Handler:sendMessage	(Landroid/os/Message;)Z
    //   174: pop
    //   175: goto -175 -> 0
    //   178: astore_1
    //   179: aload_0
    //   180: monitorexit
    //   181: aload_1
    //   182: athrow
    //   183: astore 7
    //   185: aload 7
    //   187: invokevirtual 103	java/lang/InterruptedException:printStackTrace	()V
    //   190: goto -169 -> 21
    //
    // Exception table:
    //   from	to	target	type
    //   17	21	26	finally
    //   21	23	26	finally
    //   185	190	26	finally
    //   35	53	178	finally
    //   17	21	183	java/lang/InterruptedException
  }
}

/* Location:           D:\rm_src\classes_dex2jar\
 * Qualified Name:     com.pay.image.cache.b
 * JD-Core Version:    0.6.0
 */