package com.pay.network.modle;

import com.pay.data.orderInfo.APOrderInfo;
import com.pay.data.userInfo.APUserInfo;
import com.pay.http.APBaseHttpAns;
import com.pay.http.APBaseHttpReq;
import com.pay.http.APHttpHandle;
import com.pay.http.IAPHttpAnsObserver;
import com.pay.tool.APDataInterface;
import com.pay.tool.APMonthDataInterface;
import com.pay.tool.APMonthDataInterface.MonthOpenType;
import com.pay.ui.channel.APChannelInfo;
import com.pay.ui.channel.APChannelList;
import com.pay.ui.channel.APHFAmountList;
import com.pay.ui.payCenter.APSaveValueList;
import java.text.DecimalFormat;
import java.util.ArrayList;
import java.util.HashMap;
import org.json.JSONArray;
import org.json.JSONException;
import org.json.JSONObject;

public class APMobileMonthInfoAns extends APBaseHttpAns
{
  private APOrderInfo a = APDataInterface.singleton().getOrderInfo();
  private APUserInfo b = APDataInterface.singleton().getUserInfo();

  public APMobileMonthInfoAns(APHttpHandle paramAPHttpHandle, IAPHttpAnsObserver paramIAPHttpAnsObserver, HashMap paramHashMap, String paramString)
  {
    super(paramAPHttpHandle, paramIAPHttpAnsObserver, paramHashMap, paramString);
  }

  private static void a(JSONObject paramJSONObject)
  {
    if (!paramJSONObject.has("product"))
      return;
    while (true)
    {
      JSONArray localJSONArray;
      String[] arrayOfString1;
      String[] arrayOfString2;
      String[] arrayOfString3;
      String[] arrayOfString4;
      int j;
      try
      {
        localJSONArray = paramJSONObject.getJSONArray("product");
        int i = localJSONArray.length();
        arrayOfString1 = new String[i];
        arrayOfString2 = new String[i];
        arrayOfString3 = new String[i];
        arrayOfString4 = new String[i];
        j = 0;
        if (j >= i)
        {
          APSaveValueList.singleton().setSaveValue(arrayOfString1, arrayOfString2, arrayOfString3, arrayOfString4);
          return;
        }
      }
      catch (JSONException localJSONException)
      {
        localJSONException.printStackTrace();
        return;
      }
      String str1 = ((JSONObject)localJSONArray.get(j)).getString("open_days").toString();
      String str2 = ((JSONObject)localJSONArray.get(j)).getString("currency_amt").toString();
      String str3 = ((JSONObject)localJSONArray.get(j)).getString("product_id").toString();
      String str4 = ((JSONObject)localJSONArray.get(j)).getString("product_name").toString();
      float f = Float.valueOf(str2).floatValue() / 100.0F;
      DecimalFormat localDecimalFormat = new DecimalFormat();
      localDecimalFormat.applyPattern("0.00");
      String str5 = localDecimalFormat.format(f);
      arrayOfString1[j] = str1;
      arrayOfString2[j] = str5;
      arrayOfString3[j] = str3;
      arrayOfString4[j] = str4;
      j++;
    }
  }

  private static void b(JSONObject paramJSONObject)
  {
    if (!paramJSONObject.has("recommend_list"))
      return;
    while (true)
    {
      JSONArray localJSONArray;
      String[] arrayOfString;
      int j;
      try
      {
        localJSONArray = paramJSONObject.getJSONArray("recommend_list");
        int i = localJSONArray.length();
        arrayOfString = new String[i];
        j = 0;
        if (j >= i)
        {
          APSaveValueList.singleton().setSaveValue(arrayOfString);
          return;
        }
      }
      catch (JSONException localJSONException)
      {
        localJSONException.printStackTrace();
        return;
      }
      arrayOfString[j] = localJSONArray.get(j).toString();
      j++;
    }
  }

  private static void c(JSONObject paramJSONObject)
  {
    int i;
    int j;
    do
      try
      {
        JSONArray localJSONArray = paramJSONObject.getJSONArray("hf_amt_allow");
        i = localJSONArray.length();
        APHFAmountList.singleton().clear();
        j = 0;
        continue;
        String str = localJSONArray.get(j).toString();
        APHFAmountList.singleton().addHFAmountList(str);
        j++;
      }
      catch (JSONException localJSONException)
      {
        APHFAmountList.singleton().clear();
        localJSONException.printStackTrace();
        return;
      }
    while (j < i);
  }

  private void d(JSONObject paramJSONObject)
  {
    int i = 0;
    try
    {
      localArrayList1 = new ArrayList();
      localJSONArray3 = paramJSONObject.getJSONArray("show_channel");
      int n = localJSONArray3.length();
      i1 = 0;
      if (i1 >= n)
        APChannelList.singleton().setShowCommChannelList(localArrayList1);
    }
    catch (JSONException localJSONException1)
    {
      try
      {
        label42: localJSONArray2 = paramJSONObject.getJSONArray("qqacct_save_channel");
        localArrayList3 = new ArrayList();
        int k = localJSONArray2.length();
        m = 0;
        if (m >= k)
          APChannelList.singleton().setMoreAccoutChannelList(localArrayList3);
      }
      catch (JSONException localJSONException1)
      {
        try
        {
          ArrayList localArrayList1;
          JSONArray localJSONArray3;
          int i1;
          JSONArray localJSONArray2;
          ArrayList localArrayList3;
          int m;
          label84: JSONArray localJSONArray1 = paramJSONObject.getJSONArray("channel");
          int j = localJSONArray1.length();
          ArrayList localArrayList2 = new ArrayList();
          while (true)
          {
            while (true)
            {
              while (true)
              {
                if (i < j)
                  break label348;
                APChannelList.singleton().setMoreCommChannelList(localArrayList2);
                return;
                JSONObject localJSONObject3 = (JSONObject)localJSONArray3.get(i1);
                APChannelInfo localAPChannelInfo3 = new APChannelInfo();
                localAPChannelInfo3.channelId = localJSONObject3.getString("name");
                localAPChannelInfo3.channelDiscount = String.valueOf(localJSONObject3.getInt("discount"));
                localAPChannelInfo3.channelInfo = localJSONObject3.getString("info");
                localAPChannelInfo3.channelState = 1;
                try
                {
                  String str7 = localJSONObject3.getString("channelname");
                  str6 = str7;
                  localAPChannelInfo3.channelName = str6;
                  localArrayList1.add(localAPChannelInfo3);
                  i1++;
                }
                catch (Exception localException4)
                {
                  while (true)
                    String str6 = "";
                }
              }
              localException1 = localException1;
              localException1.printStackTrace();
              break label42;
              JSONObject localJSONObject2 = (JSONObject)localJSONArray2.get(m);
              APChannelInfo localAPChannelInfo2 = new APChannelInfo();
              localAPChannelInfo2.channelId = localJSONObject2.getString("name");
              localAPChannelInfo2.channelDiscount = String.valueOf(localJSONObject2.getInt("discount"));
              localAPChannelInfo2.channelState = 2;
              try
              {
                String str5 = localJSONObject2.getString("channelname");
                str4 = str5;
                localAPChannelInfo2.channelName = str4;
                localArrayList3.add(localAPChannelInfo2);
                m++;
              }
              catch (Exception localException3)
              {
                while (true)
                  String str4 = "";
              }
            }
            localJSONException1 = localJSONException1;
            localJSONException1.printStackTrace();
            break label84;
            label348: JSONObject localJSONObject1 = (JSONObject)localJSONArray1.get(i);
            String str1 = localJSONObject1.getString("name");
            APChannelInfo localAPChannelInfo1;
            if (((this.a.saveType != 5) && ((this.a.saveType != 4) || (APMonthDataInterface.singleton().getOpenType() != APMonthDataInterface.MonthOpenType.OpenType_NoRate))) || ((!str1.equals("hfpay")) && (!str1.equals("mcard"))))
            {
              localAPChannelInfo1 = new APChannelInfo();
              localAPChannelInfo1.channelId = localJSONObject1.getString("name");
              localAPChannelInfo1.channelDiscount = String.valueOf(localJSONObject1.getInt("discount"));
              localAPChannelInfo1.channelInfo = localJSONObject1.getString("info");
              localAPChannelInfo1.channelState = 2;
            }
            try
            {
              String str3 = localJSONObject1.getString("channelname");
              str2 = str3;
              localAPChannelInfo1.channelName = str2;
              localArrayList2.add(localAPChannelInfo1);
              i++;
            }
            catch (Exception localException2)
            {
              while (true)
                String str2 = "";
            }
          }
        }
        catch (JSONException localJSONException2)
        {
          localJSONException2.printStackTrace();
        }
      }
    }
  }

  public void onErrorAns(APBaseHttpReq paramAPBaseHttpReq)
  {
  }

  // ERROR //
  public void onFinishAns(byte[] paramArrayOfByte, APBaseHttpReq paramAPBaseHttpReq)
  {
    // Byte code:
    //   0: aload_0
    //   1: aload_1
    //   2: aload_2
    //   3: invokespecial 235	com/pay/http/APBaseHttpAns:onFinishAns	([BLcom/pay/http/APBaseHttpReq;)V
    //   6: new 53	java/lang/String
    //   9: dup
    //   10: aload_1
    //   11: invokespecial 238	java/lang/String:<init>	([B)V
    //   14: astore_3
    //   15: ldc 240
    //   17: new 242	java/lang/StringBuilder
    //   20: dup
    //   21: ldc 244
    //   23: invokespecial 246	java/lang/StringBuilder:<init>	(Ljava/lang/String;)V
    //   26: aload_3
    //   27: invokevirtual 250	java/lang/StringBuilder:append	(Ljava/lang/String;)Ljava/lang/StringBuilder;
    //   30: invokevirtual 251	java/lang/StringBuilder:toString	()Ljava/lang/String;
    //   33: invokestatic 257	com/pay/common/tool/APLog:i	(Ljava/lang/String;Ljava/lang/String;)V
    //   36: new 37	org/json/JSONObject
    //   39: dup
    //   40: aload_3
    //   41: invokespecial 258	org/json/JSONObject:<init>	(Ljava/lang/String;)V
    //   44: astore 4
    //   46: aload_0
    //   47: aload 4
    //   49: ldc_w 260
    //   52: invokevirtual 76	org/json/JSONObject:getString	(Ljava/lang/String;)Ljava/lang/String;
    //   55: invokevirtual 80	java/lang/String:toString	()Ljava/lang/String;
    //   58: invokestatic 265	java/lang/Integer:parseInt	(Ljava/lang/String;)I
    //   61: putfield 268	com/pay/network/modle/APMobileMonthInfoAns:resultCode	I
    //   64: aload_0
    //   65: aload 4
    //   67: ldc_w 270
    //   70: invokevirtual 76	org/json/JSONObject:getString	(Ljava/lang/String;)Ljava/lang/String;
    //   73: invokevirtual 80	java/lang/String:toString	()Ljava/lang/String;
    //   76: putfield 273	com/pay/network/modle/APMobileMonthInfoAns:resultMsg	Ljava/lang/String;
    //   79: aload 4
    //   81: ldc 183
    //   83: invokevirtual 277	org/json/JSONObject:getJSONObject	(Ljava/lang/String;)Lorg/json/JSONObject;
    //   86: astore 6
    //   88: aload_0
    //   89: getfield 268	com/pay/network/modle/APMobileMonthInfoAns:resultCode	I
    //   92: ifne +716 -> 808
    //   95: aload_0
    //   96: getfield 24	com/pay/network/modle/APMobileMonthInfoAns:a	Lcom/pay/data/orderInfo/APOrderInfo;
    //   99: getfield 281	com/pay/data/orderInfo/APOrderInfo:buyInfo	Lcom/pay/data/buyInfo/APBaseBuyInfo;
    //   102: checkcast 283	com/pay/data/buyInfo/APBuyMonthInfo
    //   105: astore 19
    //   107: aload 19
    //   109: aload 6
    //   111: ldc_w 285
    //   114: invokevirtual 76	org/json/JSONObject:getString	(Ljava/lang/String;)Ljava/lang/String;
    //   117: putfield 288	com/pay/data/buyInfo/APBuyMonthInfo:price	Ljava/lang/String;
    //   120: aload 19
    //   122: aload 6
    //   124: ldc_w 290
    //   127: invokevirtual 76	org/json/JSONObject:getString	(Ljava/lang/String;)Ljava/lang/String;
    //   130: putfield 293	com/pay/data/buyInfo/APBuyMonthInfo:offerName	Ljava/lang/String;
    //   133: aload 6
    //   135: ldc_w 295
    //   138: invokevirtual 76	org/json/JSONObject:getString	(Ljava/lang/String;)Ljava/lang/String;
    //   141: astore 30
    //   143: aload 30
    //   145: astore 21
    //   147: aload_0
    //   148: getfield 24	com/pay/network/modle/APMobileMonthInfoAns:a	Lcom/pay/data/orderInfo/APOrderInfo;
    //   151: aload 21
    //   153: putfield 298	com/pay/data/orderInfo/APOrderInfo:expressChannel	Ljava/lang/String;
    //   156: aload 6
    //   158: ldc_w 300
    //   161: invokevirtual 41	org/json/JSONObject:has	(Ljava/lang/String;)Z
    //   164: ifeq +28 -> 192
    //   167: aload 6
    //   169: ldc_w 300
    //   172: invokevirtual 76	org/json/JSONObject:getString	(Ljava/lang/String;)Ljava/lang/String;
    //   175: ldc_w 302
    //   178: invokevirtual 227	java/lang/String:equals	(Ljava/lang/Object;)Z
    //   181: ifeq +428 -> 609
    //   184: aload_0
    //   185: getfield 30	com/pay/network/modle/APMobileMonthInfoAns:b	Lcom/pay/data/userInfo/APUserInfo;
    //   188: iconst_1
    //   189: putfield 308	com/pay/data/userInfo/APUserInfo:isCFTUser	Z
    //   192: aload 6
    //   194: ldc_w 310
    //   197: invokevirtual 41	org/json/JSONObject:has	(Ljava/lang/String;)Z
    //   200: ifeq +28 -> 228
    //   203: aload 6
    //   205: ldc_w 310
    //   208: invokevirtual 76	org/json/JSONObject:getString	(Ljava/lang/String;)Ljava/lang/String;
    //   211: ldc_w 302
    //   214: invokevirtual 227	java/lang/String:equals	(Ljava/lang/Object;)Z
    //   217: ifeq +421 -> 638
    //   220: aload_0
    //   221: getfield 30	com/pay/network/modle/APMobileMonthInfoAns:b	Lcom/pay/data/userInfo/APUserInfo;
    //   224: iconst_1
    //   225: putfield 313	com/pay/data/userInfo/APUserInfo:isKJUser	Z
    //   228: aload 6
    //   230: ldc_w 315
    //   233: invokevirtual 41	org/json/JSONObject:has	(Ljava/lang/String;)Z
    //   236: ifeq +28 -> 264
    //   239: aload 6
    //   241: ldc_w 315
    //   244: invokevirtual 76	org/json/JSONObject:getString	(Ljava/lang/String;)Ljava/lang/String;
    //   247: ldc_w 302
    //   250: invokevirtual 227	java/lang/String:equals	(Ljava/lang/Object;)Z
    //   253: ifeq +396 -> 649
    //   256: aload_0
    //   257: getfield 30	com/pay/network/modle/APMobileMonthInfoAns:b	Lcom/pay/data/userInfo/APUserInfo;
    //   260: iconst_1
    //   261: putfield 318	com/pay/data/userInfo/APUserInfo:isBindQQ	Z
    //   264: aload 6
    //   266: ldc_w 320
    //   269: invokevirtual 41	org/json/JSONObject:has	(Ljava/lang/String;)Z
    //   272: ifeq +390 -> 662
    //   275: aload 6
    //   277: ldc_w 320
    //   280: invokevirtual 76	org/json/JSONObject:getString	(Ljava/lang/String;)Ljava/lang/String;
    //   283: astore 27
    //   285: aload 27
    //   287: invokestatic 265	java/lang/Integer:parseInt	(Ljava/lang/String;)I
    //   290: istore 29
    //   292: iload 29
    //   294: istore 22
    //   296: aload_0
    //   297: getfield 30	com/pay/network/modle/APMobileMonthInfoAns:b	Lcom/pay/data/userInfo/APUserInfo;
    //   300: iload 22
    //   302: putfield 323	com/pay/data/userInfo/APUserInfo:accoutBalance	I
    //   305: aload 6
    //   307: ldc_w 325
    //   310: invokevirtual 41	org/json/JSONObject:has	(Ljava/lang/String;)Z
    //   313: ifeq +93 -> 406
    //   316: aload 6
    //   318: ldc_w 325
    //   321: invokevirtual 76	org/json/JSONObject:getString	(Ljava/lang/String;)Ljava/lang/String;
    //   324: astore 23
    //   326: aload 23
    //   328: invokestatic 265	java/lang/Integer:parseInt	(Ljava/lang/String;)I
    //   331: tableswitch	default:+29 -> 360, 1:+337->668, 2:+374->705, 3:+411->742, 4:+444->775
    //   361: aconst_null
    //   362: dstore_3
    //   363: new 204	com/pay/data/orderInfo/APOrderInfo
    //   366: dup
    //   367: aload_0
    //   368: getfield 24	com/pay/network/modle/APMobileMonthInfoAns:a	Lcom/pay/data/orderInfo/APOrderInfo;
    //   371: getfield 207	com/pay/data/orderInfo/APOrderInfo:saveType	I
    //   374: invokespecial 333	com/pay/data/orderInfo/APOrderInfo:<init>	(I)V
    //   377: putfield 336	com/pay/AndroidPay:originalOrderInfo	Lcom/pay/data/orderInfo/APOrderInfo;
    //   380: invokestatic 330	com/pay/AndroidPay:singleton	()Lcom/pay/AndroidPay;
    //   383: aload_0
    //   384: getfield 24	com/pay/network/modle/APMobileMonthInfoAns:a	Lcom/pay/data/orderInfo/APOrderInfo;
    //   387: invokevirtual 340	com/pay/data/orderInfo/APOrderInfo:clone	()Ljava/lang/Object;
    //   390: checkcast 204	com/pay/data/orderInfo/APOrderInfo
    //   393: putfield 336	com/pay/AndroidPay:originalOrderInfo	Lcom/pay/data/orderInfo/APOrderInfo;
    //   396: invokestatic 18	com/pay/tool/APDataInterface:singleton	()Lcom/pay/tool/APDataInterface;
    //   399: aload_0
    //   400: getfield 24	com/pay/network/modle/APMobileMonthInfoAns:a	Lcom/pay/data/orderInfo/APOrderInfo;
    //   403: invokevirtual 344	com/pay/tool/APDataInterface:setOrderInfo	(Lcom/pay/data/orderInfo/APOrderInfo;)V
    //   406: aload_0
    //   407: aload 6
    //   409: invokespecial 346	com/pay/network/modle/APMobileMonthInfoAns:d	(Lorg/json/JSONObject;)V
    //   412: aload 6
    //   414: invokestatic 348	com/pay/network/modle/APMobileMonthInfoAns:c	(Lorg/json/JSONObject;)V
    //   417: aload 6
    //   419: ldc_w 350
    //   422: invokevirtual 175	org/json/JSONObject:getInt	(Ljava/lang/String;)I
    //   425: iconst_1
    //   426: if_icmpne +436 -> 862
    //   429: invokestatic 355	com/pay/tool/APAppDataInterface:singleton	()Lcom/pay/tool/APAppDataInterface;
    //   432: iconst_1
    //   433: invokevirtual 359	com/pay/tool/APAppDataInterface:setIsOwnResearch	(Z)V
    //   436: invokestatic 355	com/pay/tool/APAppDataInterface:singleton	()Lcom/pay/tool/APAppDataInterface;
    //   439: iconst_1
    //   440: invokevirtual 359	com/pay/tool/APAppDataInterface:setIsOwnResearch	(Z)V
    //   443: aload 6
    //   445: ldc_w 361
    //   448: invokevirtual 277	org/json/JSONObject:getJSONObject	(Ljava/lang/String;)Lorg/json/JSONObject;
    //   451: astore 13
    //   453: aload 13
    //   455: ldc_w 363
    //   458: invokevirtual 76	org/json/JSONObject:getString	(Ljava/lang/String;)Ljava/lang/String;
    //   461: astore 14
    //   463: aload 13
    //   465: ldc_w 365
    //   468: invokevirtual 76	org/json/JSONObject:getString	(Ljava/lang/String;)Ljava/lang/String;
    //   471: astore 15
    //   473: aload 13
    //   475: ldc_w 367
    //   478: invokevirtual 175	org/json/JSONObject:getInt	(Ljava/lang/String;)I
    //   481: istore 16
    //   483: aload 13
    //   485: ldc_w 369
    //   488: invokevirtual 175	org/json/JSONObject:getInt	(Ljava/lang/String;)I
    //   491: istore 17
    //   493: aload 14
    //   495: ldc 201
    //   497: invokevirtual 227	java/lang/String:equals	(Ljava/lang/Object;)Z
    //   500: ifne +44 -> 544
    //   503: iload 17
    //   505: aload_0
    //   506: getfield 373	com/pay/network/modle/APMobileMonthInfoAns:AesEncodeKey	[Ljava/lang/String;
    //   509: arraylength
    //   510: if_icmpge +34 -> 544
    //   513: aload 14
    //   515: aload_0
    //   516: getfield 373	com/pay/network/modle/APMobileMonthInfoAns:AesEncodeKey	[Ljava/lang/String;
    //   519: iload 17
    //   521: aaload
    //   522: invokestatic 379	com/pay/tool/APToolAES:doDecode	(Ljava/lang/String;Ljava/lang/String;)Ljava/lang/String;
    //   525: iconst_0
    //   526: iload 16
    //   528: invokevirtual 383	java/lang/String:substring	(II)Ljava/lang/String;
    //   531: astore 18
    //   533: invokestatic 18	com/pay/tool/APDataInterface:singleton	()Lcom/pay/tool/APDataInterface;
    //   536: invokevirtual 28	com/pay/tool/APDataInterface:getUserInfo	()Lcom/pay/data/userInfo/APUserInfo;
    //   539: aload 18
    //   541: putfield 386	com/pay/data/userInfo/APUserInfo:uinFromSvr	Ljava/lang/String;
    //   544: invokestatic 18	com/pay/tool/APDataInterface:singleton	()Lcom/pay/tool/APDataInterface;
    //   547: invokevirtual 28	com/pay/tool/APDataInterface:getUserInfo	()Lcom/pay/data/userInfo/APUserInfo;
    //   550: aload 15
    //   552: putfield 389	com/pay/data/userInfo/APUserInfo:uinTypeFromSvr	Ljava/lang/String;
    //   555: aload 6
    //   557: ldc_w 391
    //   560: invokevirtual 76	org/json/JSONObject:getString	(Ljava/lang/String;)Ljava/lang/String;
    //   563: astore 12
    //   565: aload_0
    //   566: getfield 24	com/pay/network/modle/APMobileMonthInfoAns:a	Lcom/pay/data/orderInfo/APOrderInfo;
    //   569: aload 12
    //   571: putfield 394	com/pay/data/orderInfo/APOrderInfo:sessionToken	Ljava/lang/String;
    //   574: aload 6
    //   576: ldc_w 396
    //   579: invokevirtual 76	org/json/JSONObject:getString	(Ljava/lang/String;)Ljava/lang/String;
    //   582: ldc_w 398
    //   585: invokevirtual 227	java/lang/String:equals	(Ljava/lang/Object;)Z
    //   588: ifeq +10 -> 598
    //   591: invokestatic 18	com/pay/tool/APDataInterface:singleton	()Lcom/pay/tool/APDataInterface;
    //   594: iconst_0
    //   595: invokevirtual 401	com/pay/tool/APDataInterface:setIsSendReport	(Z)V
    //   598: invokestatic 18	com/pay/tool/APDataInterface:singleton	()Lcom/pay/tool/APDataInterface;
    //   601: aload_0
    //   602: getfield 30	com/pay/network/modle/APMobileMonthInfoAns:b	Lcom/pay/data/userInfo/APUserInfo;
    //   605: invokevirtual 405	com/pay/tool/APDataInterface:setUserInfo	(Lcom/pay/data/userInfo/APUserInfo;)V
    //   608: return
    //   609: aload_0
    //   610: getfield 30	com/pay/network/modle/APMobileMonthInfoAns:b	Lcom/pay/data/userInfo/APUserInfo;
    //   613: iconst_0
    //   614: putfield 308	com/pay/data/userInfo/APUserInfo:isCFTUser	Z
    //   617: goto -425 -> 192
    //   620: astore 5
    //   622: aload 5
    //   624: invokevirtual 66	org/json/JSONException:printStackTrace	()V
    //   627: ldc 240
    //   629: aload 5
    //   631: invokevirtual 408	org/json/JSONException:getMessage	()Ljava/lang/String;
    //   634: invokestatic 411	com/pay/common/tool/APLog:w	(Ljava/lang/String;Ljava/lang/String;)V
    //   637: return
    //   638: aload_0
    //   639: getfield 30	com/pay/network/modle/APMobileMonthInfoAns:b	Lcom/pay/data/userInfo/APUserInfo;
    //   642: iconst_0
    //   643: putfield 313	com/pay/data/userInfo/APUserInfo:isKJUser	Z
    //   646: goto -418 -> 228
    //   649: aload_0
    //   650: getfield 30	com/pay/network/modle/APMobileMonthInfoAns:b	Lcom/pay/data/userInfo/APUserInfo;
    //   653: iconst_0
    //   654: putfield 318	com/pay/data/userInfo/APUserInfo:isBindQQ	Z
    //   657: goto -393 -> 264
    //   660: astore 28
    //   662: iconst_0
    //   663: istore 22
    //   665: goto -369 -> 296
    //   668: aload_0
    //   669: getfield 24	com/pay/network/modle/APMobileMonthInfoAns:a	Lcom/pay/data/orderInfo/APOrderInfo;
    //   672: astore 26
    //   674: aload_0
    //   675: getfield 24	com/pay/network/modle/APMobileMonthInfoAns:a	Lcom/pay/data/orderInfo/APOrderInfo;
    //   678: iconst_4
    //   679: putfield 414	com/pay/data/orderInfo/APOrderInfo:originalSaveType	I
    //   682: aload 26
    //   684: iconst_4
    //   685: putfield 207	com/pay/data/orderInfo/APOrderInfo:saveType	I
    //   688: invokestatic 212	com/pay/tool/APMonthDataInterface:singleton	()Lcom/pay/tool/APMonthDataInterface;
    //   691: getstatic 417	com/pay/tool/APMonthDataInterface$MonthOpenType:OpenType_Rate	Lcom/pay/tool/APMonthDataInterface$MonthOpenType;
    //   694: invokevirtual 421	com/pay/tool/APMonthDataInterface:setOpenType	(Lcom/pay/tool/APMonthDataInterface$MonthOpenType;)V
    //   697: aload 6
    //   699: invokestatic 423	com/pay/network/modle/APMobileMonthInfoAns:b	(Lorg/json/JSONObject;)V
    //   702: goto -342 -> 360
    //   705: aload_0
    //   706: getfield 24	com/pay/network/modle/APMobileMonthInfoAns:a	Lcom/pay/data/orderInfo/APOrderInfo;
    //   709: astore 25
    //   711: aload_0
    //   712: getfield 24	com/pay/network/modle/APMobileMonthInfoAns:a	Lcom/pay/data/orderInfo/APOrderInfo;
    //   715: iconst_4
    //   716: putfield 414	com/pay/data/orderInfo/APOrderInfo:originalSaveType	I
    //   719: aload 25
    //   721: iconst_4
    //   722: putfield 207	com/pay/data/orderInfo/APOrderInfo:saveType	I
    //   725: invokestatic 212	com/pay/tool/APMonthDataInterface:singleton	()Lcom/pay/tool/APMonthDataInterface;
    //   728: getstatic 222	com/pay/tool/APMonthDataInterface$MonthOpenType:OpenType_NoRate	Lcom/pay/tool/APMonthDataInterface$MonthOpenType;
    //   731: invokevirtual 421	com/pay/tool/APMonthDataInterface:setOpenType	(Lcom/pay/tool/APMonthDataInterface$MonthOpenType;)V
    //   734: aload 6
    //   736: invokestatic 425	com/pay/network/modle/APMobileMonthInfoAns:a	(Lorg/json/JSONObject;)V
    //   739: goto -379 -> 360
    //   742: aload_0
    //   743: getfield 24	com/pay/network/modle/APMobileMonthInfoAns:a	Lcom/pay/data/orderInfo/APOrderInfo;
    //   746: iconst_5
    //   747: putfield 207	com/pay/data/orderInfo/APOrderInfo:saveType	I
    //   750: aload_0
    //   751: getfield 24	com/pay/network/modle/APMobileMonthInfoAns:a	Lcom/pay/data/orderInfo/APOrderInfo;
    //   754: iconst_5
    //   755: putfield 414	com/pay/data/orderInfo/APOrderInfo:originalSaveType	I
    //   758: invokestatic 212	com/pay/tool/APMonthDataInterface:singleton	()Lcom/pay/tool/APMonthDataInterface;
    //   761: getstatic 417	com/pay/tool/APMonthDataInterface$MonthOpenType:OpenType_Rate	Lcom/pay/tool/APMonthDataInterface$MonthOpenType;
    //   764: invokevirtual 421	com/pay/tool/APMonthDataInterface:setOpenType	(Lcom/pay/tool/APMonthDataInterface$MonthOpenType;)V
    //   767: aload 6
    //   769: invokestatic 423	com/pay/network/modle/APMobileMonthInfoAns:b	(Lorg/json/JSONObject;)V
    //   772: goto -412 -> 360
    //   775: aload_0
    //   776: getfield 24	com/pay/network/modle/APMobileMonthInfoAns:a	Lcom/pay/data/orderInfo/APOrderInfo;
    //   779: iconst_5
    //   780: putfield 207	com/pay/data/orderInfo/APOrderInfo:saveType	I
    //   783: aload_0
    //   784: getfield 24	com/pay/network/modle/APMobileMonthInfoAns:a	Lcom/pay/data/orderInfo/APOrderInfo;
    //   787: iconst_5
    //   788: putfield 414	com/pay/data/orderInfo/APOrderInfo:originalSaveType	I
    //   791: invokestatic 212	com/pay/tool/APMonthDataInterface:singleton	()Lcom/pay/tool/APMonthDataInterface;
    //   794: getstatic 222	com/pay/tool/APMonthDataInterface$MonthOpenType:OpenType_NoRate	Lcom/pay/tool/APMonthDataInterface$MonthOpenType;
    //   797: invokevirtual 421	com/pay/tool/APMonthDataInterface:setOpenType	(Lcom/pay/tool/APMonthDataInterface$MonthOpenType;)V
    //   800: aload 6
    //   802: invokestatic 425	com/pay/network/modle/APMobileMonthInfoAns:a	(Lorg/json/JSONObject;)V
    //   805: goto -445 -> 360
    //   808: aload 4
    //   810: ldc_w 427
    //   813: invokevirtual 76	org/json/JSONObject:getString	(Ljava/lang/String;)Ljava/lang/String;
    //   816: invokevirtual 80	java/lang/String:toString	()Ljava/lang/String;
    //   819: astore 7
    //   821: aload 7
    //   823: ldc 201
    //   825: invokevirtual 227	java/lang/String:equals	(Ljava/lang/Object;)Z
    //   828: ifne -411 -> 417
    //   831: aload_0
    //   832: new 242	java/lang/StringBuilder
    //   835: dup
    //   836: ldc_w 429
    //   839: invokespecial 246	java/lang/StringBuilder:<init>	(Ljava/lang/String;)V
    //   842: aload 7
    //   844: invokevirtual 250	java/lang/StringBuilder:append	(Ljava/lang/String;)Ljava/lang/StringBuilder;
    //   847: ldc_w 431
    //   850: invokevirtual 250	java/lang/StringBuilder:append	(Ljava/lang/String;)Ljava/lang/StringBuilder;
    //   853: invokevirtual 251	java/lang/StringBuilder:toString	()Ljava/lang/String;
    //   856: putfield 273	com/pay/network/modle/APMobileMonthInfoAns:resultMsg	Ljava/lang/String;
    //   859: goto -442 -> 417
    //   862: invokestatic 355	com/pay/tool/APAppDataInterface:singleton	()Lcom/pay/tool/APAppDataInterface;
    //   865: iconst_0
    //   866: invokevirtual 359	com/pay/tool/APAppDataInterface:setIsOwnResearch	(Z)V
    //   869: goto -433 -> 436
    //   872: astore 8
    //   874: aload 8
    //   876: invokevirtual 66	org/json/JSONException:printStackTrace	()V
    //   879: goto -436 -> 443
    //   882: astore 9
    //   884: aload 9
    //   886: invokevirtual 66	org/json/JSONException:printStackTrace	()V
    //   889: goto -334 -> 555
    //   892: astore 10
    //   894: aload 10
    //   896: invokevirtual 66	org/json/JSONException:printStackTrace	()V
    //   899: goto -325 -> 574
    //   902: astore 11
    //   904: aload 11
    //   906: invokevirtual 66	org/json/JSONException:printStackTrace	()V
    //   909: goto -311 -> 598
    //   912: astore 20
    //   914: ldc 201
    //   916: astore 21
    //   918: goto -771 -> 147
    //   921: astore 24
    //   923: goto -517 -> 406
    //
    // Exception table:
    //   from	to	target	type
    //   36	133	620	org/json/JSONException
    //   133	143	620	org/json/JSONException
    //   147	192	620	org/json/JSONException
    //   192	228	620	org/json/JSONException
    //   228	264	620	org/json/JSONException
    //   264	285	620	org/json/JSONException
    //   285	292	620	org/json/JSONException
    //   296	326	620	org/json/JSONException
    //   326	360	620	org/json/JSONException
    //   360	406	620	org/json/JSONException
    //   406	417	620	org/json/JSONException
    //   598	608	620	org/json/JSONException
    //   609	617	620	org/json/JSONException
    //   638	646	620	org/json/JSONException
    //   649	657	620	org/json/JSONException
    //   668	702	620	org/json/JSONException
    //   705	739	620	org/json/JSONException
    //   742	772	620	org/json/JSONException
    //   775	805	620	org/json/JSONException
    //   808	859	620	org/json/JSONException
    //   874	879	620	org/json/JSONException
    //   884	889	620	org/json/JSONException
    //   894	899	620	org/json/JSONException
    //   904	909	620	org/json/JSONException
    //   285	292	660	java/lang/Exception
    //   417	436	872	org/json/JSONException
    //   436	443	872	org/json/JSONException
    //   862	869	872	org/json/JSONException
    //   443	544	882	org/json/JSONException
    //   544	555	882	org/json/JSONException
    //   555	574	892	org/json/JSONException
    //   574	598	902	org/json/JSONException
    //   133	143	912	java/lang/Exception
    //   326	360	921	java/lang/Exception
    //   360	406	921	java/lang/Exception
    //   668	702	921	java/lang/Exception
    //   705	739	921	java/lang/Exception
    //   742	772	921	java/lang/Exception
    //   775	805	921	java/lang/Exception
  }

  public void onReceiveAns(byte[] paramArrayOfByte, int paramInt, long paramLong, APBaseHttpReq paramAPBaseHttpReq)
  {
  }

  public void onStartAns(APBaseHttpReq paramAPBaseHttpReq)
  {
  }

  public void onStopAns(APBaseHttpReq paramAPBaseHttpReq)
  {
  }
}

/* Location:           D:\rm_src\classes_dex2jar\
 * Qualified Name:     com.pay.network.modle.APMobileMonthInfoAns
 * JD-Core Version:    0.6.0
 */